setup.py
utarfile.py
micropython_utarfile.egg-info/PKG-INFO
micropython_utarfile.egg-info/SOURCES.txt
micropython_utarfile.egg-info/dependency_links.txt
micropython_utarfile.egg-info/top_level.txt